wikidl/__init__.py
wikidl/core.py
wikidl/logger_init.py
wikidl/patterns.py
wikidl/utils.py
wikidl-0.1.0.dist-info/LICENSE
wikidl-0.1.0.dist-info/WHEEL
wikidl-0.1.0.dist-info/METADATA
wikidl-0.1.0.dist-info/RECORD
